Metadata-Version: 2.1
Name: PicToCmd
Version: 0.1
Summary: A Python library to convert images to ASCII art using edge detection.
Home-page: https://github.com/486lv/PicToCmd
Author: 486lv
Author-email: 2876587146@qq.com
Keywords: ASCII,art,image,edge detection,PicToCmd
Classifier: Programming Language :: Python :: 3
Classifier: License :: OSI Approved :: MIT License
Classifier: Operating System :: OS Independent
Classifier: Intended Audience :: Developers
Classifier: Intended Audience :: End Users/Desktop
Requires-Python: >=3.6
License-File: LICENSE.txt
Requires-Dist: opencv-python>=4.5.0
Requires-Dist: numpy>=1.21.0
